odoo10_addon_l10n_de_steuernummer-10.0.1.0.0-py2.7-nspkg.pth
odoo/addons/l10n_de_steuernummer/README.rst
odoo/addons/l10n_de_steuernummer/__init__.py
odoo/addons/l10n_de_steuernummer/__manifest__.py
odoo/addons/l10n_de_steuernummer/models/__init__.py
odoo/addons/l10n_de_steuernummer/models/res_partner.py
odoo/addons/l10n_de_steuernummer/static/description/icon.png
odoo/addons/l10n_de_steuernummer/tests/__init__.py
odoo/addons/l10n_de_steuernummer/tests/test_l10n_de_steuernummer.py
odoo10_addon_l10n_de_steuernummer-10.0.1.0.0.dist-info/DESCRIPTION.rst
odoo10_addon_l10n_de_steuernummer-10.0.1.0.0.dist-info/METADATA
odoo10_addon_l10n_de_steuernummer-10.0.1.0.0.dist-info/RECORD
odoo10_addon_l10n_de_steuernummer-10.0.1.0.0.dist-info/WHEEL
odoo10_addon_l10n_de_steuernummer-10.0.1.0.0.dist-info/metadata.json
odoo10_addon_l10n_de_steuernummer-10.0.1.0.0.dist-info/namespace_packages.txt
odoo10_addon_l10n_de_steuernummer-10.0.1.0.0.dist-info/top_level.txt
